autogen/__init__.py
autogen/browser_utils.py
autogen/code_utils.py
autogen/doc_utils.py
autogen/exception_utils.py
autogen/formatting_utils.py
autogen/function_utils.py
autogen/graph_utils.py
autogen/import_utils.py
autogen/json_utils.py
autogen/math_utils.py
autogen/retrieve_utils.py
autogen/runtime_logging.py
autogen/token_count_utils.py
autogen/types.py
autogen/version.py
autogen/_website/__init__.py
autogen/_website/generate_api_references.py
autogen/_website/generate_mkdocs.py
autogen/_website/notebook_processor.py
autogen/_website/process_notebooks.py
autogen/_website/utils.py
autogen/a2a/__init__.py
autogen/a2a/agent_executor.py
autogen/a2a/client.py
autogen/a2a/errors.py
autogen/a2a/httpx_client_factory.py
autogen/a2a/server.py
autogen/a2a/utils.py
autogen/agentchat/__init__.py
autogen/agentchat/agent.py
autogen/agentchat/assistant_agent.py
autogen/agentchat/chat.py
autogen/agentchat/conversable_agent.py
autogen/agentchat/groupchat.py
autogen/agentchat/user_proxy_agent.py
autogen/agentchat/utils.py
autogen/agentchat/contrib/__init__.py
autogen/agentchat/contrib/agent_optimizer.py
autogen/agentchat/contrib/gpt_assistant_agent.py
autogen/agentchat/contrib/img_utils.py
autogen/agentchat/contrib/llamaindex_conversable_agent.py
autogen/agentchat/contrib/llava_agent.py
autogen/agentchat/contrib/math_user_proxy_agent.py
autogen/agentchat/contrib/multimodal_conversable_agent.py
autogen/agentchat/contrib/qdrant_retrieve_user_proxy_agent.py
autogen/agentchat/contrib/retrieve_assistant_agent.py
autogen/agentchat/contrib/retrieve_user_proxy_agent.py
autogen/agentchat/contrib/society_of_mind_agent.py
autogen/agentchat/contrib/swarm_agent.py
autogen/agentchat/contrib/text_analyzer_agent.py
autogen/agentchat/contrib/web_surfer.py
autogen/agentchat/contrib/agent_eval/README.md
autogen/agentchat/contrib/agent_eval/agent_eval.py
autogen/agentchat/contrib/agent_eval/criterion.py
autogen/agentchat/contrib/agent_eval/critic_agent.py
ag2-0.10.5.dist-info/METADATA
ag2-0.10.5.dist-info/WHEEL
ag2-0.10.5.dist-info/licenses/LICENSE
ag2-0.10.5.dist-info/licenses/NOTICE.md
ag2-0.10.5.dist-info/RECORD
